autoconda.py
autoconda-0.4.1.dist-info/METADATA
autoconda-0.4.1.dist-info/WHEEL
autoconda-0.4.1.dist-info/entry_points.txt
autoconda-0.4.1.dist-info/licenses/LICENSE
autoconda-0.4.1.dist-info/RECORD
