Metadata-Version: 2.4
Name: autoconda
Version: 0.4.1
Author-email: Gediminas Zlatkus <gediminas.zlatkus@gmail.com>
License-File: LICENSE
Requires-Python: >=3.10
Requires-Dist: pyyaml
